nicknames/__init__.py
nicknames/_csvfile.py
nicknames/_nicknamer.py
nicknames/_version.py
nicknames/names.csv
nicknames/py.typed
nicknames-1.0.0.dist-info/METADATA
nicknames-1.0.0.dist-info/WHEEL
nicknames-1.0.0.dist-info/RECORD
