Metadata-Version: 2.4
Name: nicknames
Version: 1.0.0
Summary: Hand-curated dataset of English names and nicknames.
Project-URL: Homepage, https://github.com/carltonnorthern/nicknames
Project-URL: Bug Tracker, https://github.com/carltonnorthern/nicknames/issues
Author-email: Carlton Northern <carlton.northern@gmail.com>, Nick Crews <nicholas.b.crews@gmail.com>
License-Expression: Apache-2.0
Classifier: Development Status :: 4 - Beta
Classifier: License :: OSI Approved :: Apache Software License
Classifier: Natural Language :: English
Classifier: Operating System :: OS Independent
Classifier: Programming Language :: Python :: 3
Classifier: Programming Language :: Python :: 3.8
Classifier: Programming Language :: Python :: 3.9
Classifier: Programming Language :: Python :: 3.10
Classifier: Programming Language :: Python :: 3.11
Classifier: Programming Language :: Python :: 3.12
Classifier: Programming Language :: Python :: 3.13
Classifier: Programming Language :: Python :: 3.14
Classifier: Topic :: Scientific/Engineering :: Information Analysis
Classifier: Topic :: Sociology :: Genealogy
Classifier: Topic :: Software Development :: Libraries
Classifier: Topic :: Text Processing
Classifier: Topic :: Text Processing :: Linguistic
Classifier: Typing :: Typed
Requires-Python: >=3.8
